[
 {
  "fid": 1,
  "Type": "AB",
  "Name": "tolam",
  "s_lng": 99.91153,
  "s_lat": 18.43687,
  "t_lng": 99.337375,
  "t_lat": 18.2926485,
  "size": 2,
  "s_color": [144,151,96],
  "t_color": [119,125,80]
 },
 {
  "fid": 2,
  "Type": "AB",
  "Name": "tolam",
  "s_lng": 98.789007,
  "s_lat": 18.48335814,
  "t_lng": 99.337375,
  "t_lat": 18.2926485,
  "size": 2,
  "s_color": [144,151,96],
  "t_color": [119,125,80]
 },
 {
  "fid": 3,
  "Type": "AB",
  "Name": "tolam",
  "s_lng": 99.5684819,
  "s_lat": 18.3403194245,
  "t_lng": 99.337375,
  "t_lat": 18.2926485,
  "size": 2,
  "s_color": [144,151,96],
  "t_color": [119,125,80]
 },
 {
  "fid": 4,
  "Type": "AB",
  "Name": "tolam",
  "s_lng": 98.90261,
  "s_lat": 17.91867,
  "t_lng": 99.337375,
  "t_lat": 18.2926485,
  "size": 2,
  "s_color": [144,151,96],
  "t_color": [119,125,80]
 },
 {
  "fid": 5,
  "Type": "AB",
  "Name": "tolam",
  "s_lng": 99.23211,
  "s_lat": 18.05211,
  "t_lng": 99.337375,
  "t_lat": 18.2926485,
  "size": 2,
  "s_color": [144,151,96],
  "t_color": [119,125,80]
 },
 {
  "fid": 6,
  "Type": "AB",
  "Name": "tolam",
  "s_lng": 99.56091,
  "s_lat": 18.69895,
  "t_lng": 99.337375,
  "t_lat": 18.2926485,
  "size": 2,
  "s_color": [144,151,96],
  "t_color": [119,125,80]
 },
 {
  "fid": 7,
  "Type": "AB",
  "Name": "toprae",
  "s_lng": 100.344491304648,
  "s_lat": 17.5940510510749,
  "t_lng": 100.357562090111,
  "t_lat": 17.63976635,
  "size": 2,
  "s_color": [144,151,96],
  "t_color": [119,125,80]
 },
 {
  "fid": 8,
  "Type": "AB",
  "Name": "toprae",
  "s_lng": 100.14795336688,
  "s_lat": 17.419864993,
  "t_lng": 100.357562090111,
  "t_lat": 17.63976635,
  "size": 2,
  "s_color": [144,151,96],
  "t_color": [119,125,80]
 },
 {
  "fid": 9,
  "Type": "AB",
  "Name": "toutt",
  "s_lng": 100.0087269,
  "s_lat": 17.61883979,
  "t_lng": 100.11238792,
  "t_lat": 17.5861839,
  "size": 2,
  "s_color": [144,151,96],
  "t_color": [119,125,80]
 },
 {
  "fid": 10,
  "Type": "AB",
  "Name": "toutt",
  "s_lng": 99.96502874,
  "s_lat": 17.528616,
  "t_lng": 100.11238792,
  "t_lat": 17.5861839,
  "size": 2,
  "s_color": [144,151,96],
  "t_color": [119,125,80]
 },
 {
  "fid": 11,
  "Type": "AB",
  "Name": "toutt",
  "s_lng": 100.118652133997,
  "s_lat": 17.4120146922521,
  "t_lng": 100.11238792,
  "t_lat": 17.5861839,
  "size": 2,
  "s_color": [144,151,96],
  "t_color": [119,125,80]
 },
 {
  "fid": 12,
  "Type": "BC",
  "Name": "topra",
  "s_lng": 99.337375,
  "s_lat": 18.2926485,
  "t_lng": 101.38505,
  "t_lat": 14.054725,
  "size": 4,
  "s_color": [119,125,80],
  "t_color": [89,96,81]
 },
 {
  "fid": 13,
  "Type": "BC",
  "Name": "topra",
  "s_lng": 100.357562090111,
  "s_lat": 17.63976635,
  "t_lng": 101.38505,
  "t_lat": 14.054725,
  "size": 4,
  "s_color": [119,125,80],
  "t_color": [89,96,81]
 },
 {
  "fid": 14,
  "Type": "BC",
  "Name": "topra",
  "s_lng": 100.11238792,
  "s_lat": 17.5861839,
  "t_lng": 101.38505,
  "t_lat": 14.054725,
  "size": 4,
  "s_color": [119,125,80],
  "t_color": [89,96,81]
 },
 {
  "fid": 15,
  "Type": "CD",
  "Name": "tobkk",
  "s_lng": 101.38505,
  "s_lat": 14.054725,
  "t_lng": 100.669051253982,
  "t_lat": 13.6562793426678,
  "size": 3,
  "s_color": [89,96,81],
  "t_color": [55,53,92]
 },
 {
  "fid": 16,
  "Type": "CD",
  "Name": "tophu",
  "s_lng": 101.38505,
  "s_lat": 14.054725,
  "t_lng": 98.2964484677728,
  "t_lat": 8.172962162,
  "size": 3,
  "s_color": [89,96,81],
  "t_color": [55,53,92]
 },
 {
  "fid": 17,
  "Type": "CD",
  "Name": "tocnx",
  "s_lng": 101.38505,
  "s_lat": 14.054725,
  "t_lng": 99.0038105409082,
  "t_lat": 18.7816562918,
  "size": 3,
  "s_color": [89,96,81],
  "t_color": [55,53,92]
 },
 {
  "fid": 18,
  "Type": "AB",
  "Name": "totest1",
  "s_lng": 101.87225,
  "s_lat": 12.82916,
  "t_lng": 101.8586,
  "t_lat": 12.9808,
  "size": 2,
  "s_color": [255,149,209],
  "t_color": [255,58,222]
 },
 {
  "fid": 19,
  "Type": "AB",
  "Name": "totest1",
  "s_lng": 101.52243,
  "s_lat": 12.82436,
  "t_lng": 101.8586,
  "t_lat": 12.9808,
  "size": 2,
  "s_color": [255,149,209],
  "t_color": [255,58,222]
 },
 {
  "fid": 20,
  "Type": "AB",
  "Name": "totest1",
  "s_lng": 101.77407,
  "s_lat": 13.111786,
  "t_lng": 101.8586,
  "t_lat": 12.9808,
  "size": 2,
  "s_color": [255,149,209],
  "t_color": [255,58,222]
 },
 {
  "fid": 21,
  "Type": "AB",
  "Name": "totest2",
  "s_lng": 102.4034,
  "s_lat": 13.7191,
  "t_lng": 102.22805,
  "t_lat": 13.82456,
  "size": 2,
  "s_color": [255,149,209],
  "t_color": [255,58,222]
 },
 {
  "fid": 22,
  "Type": "AB",
  "Name": "totest2",
  "s_lng": 102.68056,
  "s_lat": 13.978,
  "t_lng": 102.22805,
  "t_lat": 13.82456,
  "size": 2,
  "s_color": [255,149,209],
  "t_color": [255,58,222]
 },
 {
  "fid": 23,
  "Type": "AB",
  "Name": "totest2",
  "s_lng": 102.17355,
  "s_lat": 13.5203,
  "t_lng": 102.22805,
  "t_lat": 13.82456,
  "size": 2,
  "s_color": [255,149,209],
  "t_color": [255,58,222]
 },
 {
  "fid": 24,
  "Type": "AB",
  "Name": "totest3",
  "s_lng": 101.72087,
  "s_lat": 13.33869,
  "t_lng": 101.61469,
  "t_lat": 13.58053,
  "size": 2,
  "s_color": [255,149,209],
  "t_color": [255,58,222]
 },
 {
  "fid": 25,
  "Type": "AB",
  "Name": "totest3",
  "s_lng": 101.54302,
  "s_lat": 13.34284,
  "t_lng": 101.61469,
  "t_lat": 13.58053,
  "size": 2,
  "s_color": [255,149,209],
  "t_color": [255,58,222]
 },
 {
  "fid": 26,
  "Type": "BC",
  "Name": "topra",
  "s_lng": 101.8586,
  "s_lat": 12.9808,
  "t_lng": 101.38505,
  "t_lat": 14.054725,
  "size": 4,
  "s_color": [255,58,222],
  "t_color": [22,146,97]
 },
 {
  "fid": 27,
  "Type": "BC",
  "Name": "topra",
  "s_lng": 102.22805,
  "s_lat": 13.82456,
  "t_lng": 101.38505,
  "t_lat": 14.054725,
  "size": 4,
  "s_color": [255,58,222],
  "t_color": [22,146,97]
 },
 {
  "fid": 28,
  "Type": "BC",
  "Name": "topra",
  "s_lng": 101.61469,
  "s_lat": 13.58053,
  "t_lng": 101.38505,
  "t_lat": 14.054725,
  "size": 4,
  "s_color": [255,58,222],
  "t_color": [22,146,97]
 }
]
